PairwiseNameComparator.cpython-39-x86_64-linux-gnu.so
pairwisenamecomparator.libs/libgomp-e985bcbb.so.1.0.0
pairwisenamecomparator-0.1.0.dist-info/METADATA
pairwisenamecomparator-0.1.0.dist-info/WHEEL
pairwisenamecomparator-0.1.0.dist-info/top_level.txt
pairwisenamecomparator-0.1.0.dist-info/RECORD
pairwisenamecomparator-0.1.0.dist-info/licenses/LICENSE
