Metadata-Version: 2.1
Name: PairwiseNameComparator
Version: 0.1.0
Summary: Fast parallel dictionary lookups using Cython and OpenMP
Requires-Python: >=3.8
License-File: LICENSE
